{
  "id": "MAP_BRAWLY_DOJO_REMATCH_ROOM",
  "name": "BrawlyDojoRematchRoom",
  "layout": "LAYOUT_BRAWLY_DOJO_REMATCH_ROOM",
  "music": "MUS_DP_GTS",
  "region_map_section": "MAPSEC_DEWFORD_DOJO",
  "requires_flash": false,
  "weather": "WEATHER_NONE",
  "map_type": "MAP_TYPE_INDOOR",
  "allow_cycling": false,
  "allow_escaping": false,
  "allow_running": true,
  "show_map_name": false,
  "battle_scene": "MAP_BATTLE_SCENE_NORMAL",
  "connections": 0,
  "object_events": [
    {
      "graphics_id": "OBJ_EVENT_GFX_BRAWLY",
      "x": 12,
      "y": 13,
      "elevation": 0,
      "movement_type": "MOVEMENT_TYPE_FACE_LEFT",
      "movement_range_x": 0,
      "movement_range_y": 0,
      "trainer_type": "TRAINER_TYPE_NONE",
      "trainer_sight_or_berry_tree_id": "0",
      "script": "NULL",
      "flag": "FLAG_DEWFORD_GYM_GUARD"
    },
    {
      "graphics_id": "OBJ_EVENT_GFX_BLACK_BELT",
      "x": 8,
      "y": 13,
      "elevation": 0,
      "movement_type": "MOVEMENT_TYPE_FACE_UP",
      "movement_range_x": 0,
      "movement_range_y": 0,
      "trainer_type": "TRAINER_TYPE_NONE",
      "trainer_sight_or_berry_tree_id": "0",
      "script": "BrawlyDojoRematchRoomBlackbelt",
      "flag": "0"
    },
    {
      "graphics_id": "OBJ_EVENT_GFX_GIRL_1",
      "x": 10,
      "y": 10,
      "elevation": 0,
      "movement_type": "MOVEMENT_TYPE_WANDER_AROUND",
      "movement_range_x": 1,
      "movement_range_y": 1,
      "trainer_type": "TRAINER_TYPE_NONE",
      "trainer_sight_or_berry_tree_id": "0",
      "script": "BrawlyDojoRematchRoomGirl",
      "flag": "0"
    },
    {
      "graphics_id": "OBJ_EVENT_GFX_CHUCK",
      "x": 11,
      "y": 13,
      "elevation": 0,
      "movement_type": "MOVEMENT_TYPE_FACE_RIGHT",
      "movement_range_x": 0,
      "movement_range_y": 0,
      "trainer_type": "TRAINER_TYPE_NONE",
      "trainer_sight_or_berry_tree_id": "0",
      "script": "NULL",
      "flag": "FLAG_DEWFORD_GYM_GUARD"
    },
    {
      "graphics_id": "OBJ_EVENT_GFX_BOY_3",
      "x": 4,
      "y": 10,
      "elevation": 0,
      "movement_type": "MOVEMENT_TYPE_FACE_RIGHT",
      "movement_range_x": 0,
      "movement_range_y": 0,
      "trainer_type": "TRAINER_TYPE_NONE",
      "trainer_sight_or_berry_tree_id": "0",
      "script": "NULL",
      "flag": "0"
    },
    {
      "graphics_id": "OBJ_EVENT_GFX_MON_BASE+SPECIES_MANKEY",
      "x": 19,
      "y": 8,
      "elevation": 0,
      "movement_type": "MOVEMENT_TYPE_FACE_LEFT",
      "movement_range_x": 0,
      "movement_range_y": 0,
      "trainer_type": "TRAINER_TYPE_NONE",
      "trainer_sight_or_berry_tree_id": "0",
      "script": "BrawlyDojoRematchRoomMankey",
      "flag": "0"
    },
    {
      "graphics_id": "OBJ_EVENT_GFX_GIRL_3",
      "x": 3,
      "y": 7,
      "elevation": 0,
      "movement_type": "MOVEMENT_TYPE_FACE_RIGHT",
      "movement_range_x": 0,
      "movement_range_y": 0,
      "trainer_type": "TRAINER_TYPE_NONE",
      "trainer_sight_or_berry_tree_id": "0",
      "script": "NULL",
      "flag": "0"
    }
  ],
  "warp_events": [
    {
      "x": 12,
      "y": 19,
      "elevation": 0,
      "dest_map": "MAP_BRAWLY_DOJO",
      "dest_warp_id": "3"
    },
    {
      "x": 11,
      "y": 19,
      "elevation": 0,
      "dest_map": "MAP_BRAWLY_DOJO",
      "dest_warp_id": "3"
    }
  ],
  "coord_events": [
    {
      "type": "trigger",
      "x": 12,
      "y": 16,
      "elevation": 0,
      "var": "VAR_DEWFORD_TOWN_STATE",
      "var_value": "0",
      "script": "BrawlyDojoBrawlyNPC"
    },
    {
      "type": "trigger",
      "x": 11,
      "y": 16,
      "elevation": 0,
      "var": "VAR_DEWFORD_TOWN_STATE",
      "var_value": "0",
      "script": "BrawlyDojoBrawlyNPC"
    }
  ],
  "bg_events": [

  ]
}
